{"name":"nav","id":"操作系统-nav","content":"# 操作系统\n\n- 管理计算机硬件与软件资源的程序\n- 运行在计算机上的一个软件\n- 分为内核与外壳（我们可以把外壳理解成围绕着内核的应用程序，而内核就是能操作硬件的程序）\n\n## 基本特征\n\n### 并发\n\n并发是指宏观上在一段时间内能同时运行多个程序，而并行则指同一时刻能运行多个指令\n并发需要硬件支持\n操作系统引入进程和线程，使得程序能够并发执行\n\n### 共享\n\n系统中的资源可以被多个并发进程共同使用\n\n- 互斥共享\n  - 临界资源，这种资源共享需要使用同步机制来实现互斥访问\n- 同时共享\n\n### 虚拟\n\n- 时分复用\n  - 多个进程能在同一个处理上运行（每个进程轮流使用处理器，快速进行切换）\n- 空分复用\n  - 虚拟内存中的页映射，进程地址空间的内存可以不用全在物理内存中，一些可以放在外存，当需要这些内存的时候，通过页面置换算法，移到内存当中\n\n### 异步\n\n进程不一次性执行完毕，以不确定的速度前进\n\n## 基本功能\n\n- 进程管理\n- 内存管理\n- 文件管理\n- 设备管理\n\n## 系统调用\n\n用户态(user mode) : 用户态运行的进程或可以直接读取用户程序的数据。\n\n内核态(kernel mode):可以简单的理解系统态运行的进程或程序几乎可以访问计算机的任何资源，不受限制\n\n进程需要使用一些功能，通过系统调用陷入内核，由操作系统代为完成\n\n![202031161057](/assets/202031161057.png)\n\n## 内核\n\n### 大内核\n\n操作系统功能作为一个紧密的整体\n\n- 性能很高\n\n### 微内核\n\n将一些功能独立出内核，划分成服务，降低内核的复杂性\n\n- 会有一定的性能损失\n\n![202031161322](/assets/202031161322.jpg)\n\n## 中断\n\n### 外中断\n\nCPU执行指令外的事件引起，IO完成中断、时钟中断等\n\n### 异常\n\nCPU执行指令引起的，地址越界、算术溢出\n\n### 陷入\n\n在用户程序中使用系统调用","metadata":"","hasMoreCommit":false,"totalCommits":9,"commitList":[{"date":"2020-08-06T09:26:14+08:00","author":"MY","message":"✏更新 操作系统基础","hash":"453ef58b0ff541b85a2174ea5293775ea4bf1c20"},{"date":"2020-03-01T16:17:35+08:00","author":"MY","message":"操作系统 增加概述","hash":"a39333fa5f755c3a221dee02609ed7e569e67990"},{"date":"2020-02-21T20:07:45+08:00","author":"MY","message":"更新部分目录结构","hash":"413e15a875001cf552a13ccaa253cdca01947610"},{"date":"2019-07-09T15:16:11+08:00","author":"My","message":"20190709u","hash":"9d0a630633492c7a9f6ca7fa3f4cc9673cd0d623"},{"date":"2019-07-06T11:55:58+08:00","author":"My","message":"20190706","hash":"83a03f95e0ae02e0dcdda71139cc3e596f295779"},{"date":"2019-07-05T14:31:04+08:00","author":"My","message":"20190705","hash":"4f208c321252e5e648f7f5665b032cf311d7fb41"},{"date":"2019-07-05T12:28:07+08:00","author":"My","message":"20190705u","hash":"b2167ed370c3b392e41171b1d62e252a9b1513a4"},{"date":"2019-06-18T18:21:48+08:00","author":"My","message":"20190618u","hash":"bfffb71a004835ff3bbbabdc51b2a8fb38dafb93"},{"date":"2019-06-12T16:41:51+08:00","author":"My","message":"20190612u","hash":"dba01a42e9a03cb3889432e22921a9e182d1c243"}],"createTime":"2019-06-12T16:41:51+08:00"}